odoo8_addon_website_event_type_description-8.0.1.1.0-py2.7-nspkg.pth
odoo_addons/website_event_type_description/__openerp__.py
odoo_addons/website_event_type_description/__init__.py
odoo_addons/website_event_type_description/README.rst
odoo_addons/website_event_type_description/models/__init__.py
odoo_addons/website_event_type_description/models/event.py
odoo_addons/website_event_type_description/i18n/es.po
odoo_addons/website_event_type_description/views/event.xml
odoo_addons/website_event_type_description/views/event_type_view.xml
odoo_addons/website_event_type_description/images/seminars.png
odoo_addons/website_event_type_description/images/all.png
odoo_addons/website_event_type_description/static/description/icon.png
odoo8_addon_website_event_type_description-8.0.1.1.0.dist-info/top_level.txt
odoo8_addon_website_event_type_description-8.0.1.1.0.dist-info/WHEEL
odoo8_addon_website_event_type_description-8.0.1.1.0.dist-info/RECORD
odoo8_addon_website_event_type_description-8.0.1.1.0.dist-info/metadata.json
odoo8_addon_website_event_type_description-8.0.1.1.0.dist-info/DESCRIPTION.rst
odoo8_addon_website_event_type_description-8.0.1.1.0.dist-info/METADATA
odoo8_addon_website_event_type_description-8.0.1.1.0.dist-info/namespace_packages.txt
